nombre_normalizer/__init__.py
nombre_normalizer/cli.py
nombre_normalizer/nombre_normalizer.py
nombre_normalizer_es-1.0.4.dist-info/licenses/LICENSE
nombre_normalizer_es-1.0.4.dist-info/METADATA
nombre_normalizer_es-1.0.4.dist-info/WHEEL
nombre_normalizer_es-1.0.4.dist-info/entry_points.txt
nombre_normalizer_es-1.0.4.dist-info/top_level.txt
nombre_normalizer_es-1.0.4.dist-info/RECORD
