Metadata-Version: 2.4
Name: nombre-normalizer-es
Version: 1.0.4
Summary: Biblioteca completa para normalizar nombres y apellidos en español con redistribución inteligente y detección de patrones
Author-email: KC <rmr@keepcoding.io>
Maintainer-email: KC <rmr@keepcoding.io>
License: MIT
Project-URL: Homepage, https://github.com/KeepCoding/normalize_tools
Project-URL: Documentation, https://github.com/KeepCoding/normalize_tools#readme
Project-URL: Repository, https://github.com/KeepCoding/normalize_tools
Project-URL: Bug Tracker, https://github.com/KeepCoding/normalize_tools/issues
Project-URL: Changelog, https://github.com/KeepCoding/normalize_tools/blob/main/CHANGELOG.md
Keywords: nombres,apellidos,normalización,español,spanish,names,normalization,nlp,text-processing,data-cleaning
Classifier: Development Status :: 5 - Production/Stable
Classifier: Intended Audience :: Developers
Classifier: Intended Audience :: Science/Research
Classifier: License :: OSI Approved :: MIT License
Classifier: Operating System :: OS Independent
Classifier: Programming Language :: Python :: 3
Classifier: Programming Language :: Python :: 3.8
Classifier: Programming Language :: Python :: 3.9
Classifier: Programming Language :: Python :: 3.10
Classifier: Programming Language :: Python :: 3.11
Classifier: Programming Language :: Python :: 3.12
Classifier: Topic :: Software Development :: Libraries :: Python Modules
Classifier: Topic :: Text Processing :: Linguistic
Classifier: Topic :: Scientific/Engineering :: Information Analysis
Classifier: Natural Language :: Spanish
Requires-Python: >=3.8
License-File: LICENSE
Requires-Dist: unicodedata2>=15.0.0; python_version < "3.13"
Provides-Extra: dev
Requires-Dist: pytest>=7.0.0; extra == "dev"
Requires-Dist: pytest-cov>=4.0.0; extra == "dev"
Requires-Dist: black>=22.0.0; extra == "dev"
Requires-Dist: flake8>=4.0.0; extra == "dev"
Requires-Dist: mypy>=1.0.0; extra == "dev"
Requires-Dist: pre-commit>=2.20.0; extra == "dev"
Provides-Extra: docs
Requires-Dist: sphinx>=5.0.0; extra == "docs"
Requires-Dist: sphinx-rtd-theme>=1.0.0; extra == "docs"
Provides-Extra: test
Requires-Dist: pytest>=7.0.0; extra == "test"
Requires-Dist: pytest-cov>=4.0.0; extra == "test"
Requires-Dist: pytest-mock>=3.10.0; extra == "test"
Dynamic: license-file
